{
  "definitions": [
    {
      "type": {
        "name": "hydra.ext.org.apache.tinkerpop.features.DataTypeFeatures",
        "type": {
          "annotated": {
            "annotation": [
              {
                "@key": "description",
                "@value": {
                  "literal": {
                    "string": "Base interface for features that relate to supporting different data types."}}}],
            "body": {
              "record": [
                {
                  "name": "supportsBooleanArrayValues",
                  "type": {
                    "annotated": {
                      "annotation": [
                        {
                          "@key": "description",
                          "@value": {
                            "literal": {"string": "Supports setting of an array of boolean values."}}}],
                      "body": {"literal": {"boolean": {}}}}}},
                {
                  "name": "supportsBooleanValues",
                  "type": {
                    "annotated": {
                      "annotation": [
                        {
                          "@key": "description",
                          "@value": {"literal": {"string": "Supports setting of a boolean value."}}}],
                      "body": {"literal": {"boolean": {}}}}}},
                {
                  "name": "supportsByteArrayValues",
                  "type": {
                    "annotated": {
                      "annotation": [
                        {
                          "@key": "description",
                          "@value": {
                            "literal": {"string": "Supports setting of an array of byte values."}}}],
                      "body": {"literal": {"boolean": {}}}}}},
                {
                  "name": "supportsByteValues",
                  "type": {
                    "annotated": {
                      "annotation": [
                        {
                          "@key": "description",
                          "@value": {"literal": {"string": "Supports setting of a byte value."}}}],
                      "body": {"literal": {"boolean": {}}}}}},
                {
                  "name": "supportsDoubleArrayValues",
                  "type": {
                    "annotated": {
                      "annotation": [
                        {
                          "@key": "description",
                          "@value": {
                            "literal": {"string": "Supports setting of an array of double values."}}}],
                      "body": {"literal": {"boolean": {}}}}}},
                {
                  "name": "supportsDoubleValues",
                  "type": {
                    "annotated": {
                      "annotation": [
                        {
                          "@key": "description",
                          "@value": {"literal": {"string": "Supports setting of a double value."}}}],
                      "body": {"literal": {"boolean": {}}}}}},
                {
                  "name": "supportsFloatArrayValues",
                  "type": {
                    "annotated": {
                      "annotation": [
                        {
                          "@key": "description",
                          "@value": {
                            "literal": {"string": "Supports setting of an array of float values."}}}],
                      "body": {"literal": {"boolean": {}}}}}},
                {
                  "name": "supportsFloatValues",
                  "type": {
                    "annotated": {
                      "annotation": [
                        {
                          "@key": "description",
                          "@value": {"literal": {"string": "Supports setting of a float value."}}}],
                      "body": {"literal": {"boolean": {}}}}}},
                {
                  "name": "supportsIntegerArrayValues",
                  "type": {
                    "annotated": {
                      "annotation": [
                        {
                          "@key": "description",
                          "@value": {
                            "literal": {"string": "Supports setting of an array of integer values."}}}],
                      "body": {"literal": {"boolean": {}}}}}},
                {
                  "name": "supportsIntegerValues",
                  "type": {
                    "annotated": {
                      "annotation": [
                        {
                          "@key": "description",
                          "@value": {"literal": {"string": "Supports setting of a integer value."}}}],
                      "body": {"literal": {"boolean": {}}}}}},
                {
                  "name": "supportsLongArrayValues",
                  "type": {
                    "annotated": {
                      "annotation": [
                        {
                          "@key": "description",
                          "@value": {
                            "literal": {"string": "Supports setting of an array of long values."}}}],
                      "body": {"literal": {"boolean": {}}}}}},
                {
                  "name": "supportsLongValues",
                  "type": {
                    "annotated": {
                      "annotation": [
                        {
                          "@key": "description",
                          "@value": {"literal": {"string": "Supports setting of a long value."}}}],
                      "body": {"literal": {"boolean": {}}}}}},
                {
                  "name": "supportsMapValues",
                  "type": {
                    "annotated": {
                      "annotation": [
                        {
                          "@key": "description",
                          "@value": {"literal": {"string": "Supports setting of a Map value."}}}],
                      "body": {"literal": {"boolean": {}}}}}},
                {
                  "name": "supportsMixedListValues",
                  "type": {
                    "annotated": {
                      "annotation": [
                        {
                          "@key": "description",
                          "@value": {"literal": {"string": "Supports setting of a List value."}}}],
                      "body": {"literal": {"boolean": {}}}}}},
                {
                  "name": "supportsSerializableValues",
                  "type": {
                    "annotated": {
                      "annotation": [
                        {
                          "@key": "description",
                          "@value": {
                            "literal": {"string": "Supports setting of a Java serializable value."}}}],
                      "body": {"literal": {"boolean": {}}}}}},
                {
                  "name": "supportsStringArrayValues",
                  "type": {
                    "annotated": {
                      "annotation": [
                        {
                          "@key": "description",
                          "@value": {
                            "literal": {"string": "Supports setting of an array of string values."}}}],
                      "body": {"literal": {"boolean": {}}}}}},
                {
                  "name": "supportsStringValues",
                  "type": {
                    "annotated": {
                      "annotation": [
                        {
                          "@key": "description",
                          "@value": {"literal": {"string": "Supports setting of a string value."}}}],
                      "body": {"literal": {"boolean": {}}}}}},
                {
                  "name": "supportsUniformListValues",
                  "type": {
                    "annotated": {
                      "annotation": [
                        {
                          "@key": "description",
                          "@value": {"literal": {"string": "Supports setting of a List value."}}}],
                      "body": {"literal": {"boolean": {}}}}}}]}}}}},
    {
      "type": {
        "name": "hydra.ext.org.apache.tinkerpop.features.EdgeFeatures",
        "type": {
          "annotated": {
            "annotation": [
              {
                "@key": "description",
                "@value": {
                  "literal": {"string": "Features that are related to Edge operations."}}}],
            "body": {
              "record": [
                {
                  "name": "elementFeatures",
                  "type": {
                    "variable": "hydra.ext.org.apache.tinkerpop.features.ElementFeatures"}},
                {
                  "name": "properties",
                  "type": {
                    "variable": "hydra.ext.org.apache.tinkerpop.features.EdgePropertyFeatures"}},
                {
                  "name": "supportsAddEdges",
                  "type": {
                    "annotated": {
                      "annotation": [
                        {
                          "@key": "description",
                          "@value": {
                            "literal": {"string": "Determines if an Edge can be added to a Vertex."}}}],
                      "body": {"literal": {"boolean": {}}}}}},
                {
                  "name": "supportsRemoveEdges",
                  "type": {
                    "annotated": {
                      "annotation": [
                        {
                          "@key": "description",
                          "@value": {
                            "literal": {"string": "Determines if an Edge can be removed from a Vertex."}}}],
                      "body": {"literal": {"boolean": {}}}}}},
                {
                  "name": "supportsUpsert",
                  "type": {
                    "annotated": {
                      "annotation": [
                        {
                          "@key": "description",
                          "@value": {
                            "literal": {
                              "string": "Determines if the Graph implementation uses upsert functionality as opposed to insert functionality for Vertex.addEdge(String, Vertex, Object...)."}}}],
                      "body": {"literal": {"boolean": {}}}}}}]}}}}},
    {
      "type": {
        "name": "hydra.ext.org.apache.tinkerpop.features.EdgePropertyFeatures",
        "type": {
          "annotated": {
            "annotation": [
              {
                "@key": "description",
                "@value": {
                  "literal": {"string": "Features that are related to Edge Property objects."}}}],
            "body": {
              "record": [
                {
                  "name": "propertyFeatures",
                  "type": {
                    "variable": "hydra.ext.org.apache.tinkerpop.features.PropertyFeatures"}}]}}}}},
    {
      "type": {
        "name": "hydra.ext.org.apache.tinkerpop.features.ElementFeatures",
        "type": {
          "annotated": {
            "annotation": [
              {
                "@key": "description",
                "@value": {
                  "literal": {"string": "Features that are related to Element objects."}}}],
            "body": {
              "record": [
                {
                  "name": "supportsAddProperty",
                  "type": {
                    "annotated": {
                      "annotation": [
                        {
                          "@key": "description",
                          "@value": {
                            "literal": {"string": "Determines if an Element allows properties to be added."}}}],
                      "body": {"literal": {"boolean": {}}}}}},
                {
                  "name": "supportsAnyIds",
                  "type": {
                    "annotated": {
                      "annotation": [
                        {
                          "@key": "description",
                          "@value": {
                            "literal": {
                              "string": "Determines if an Element any Java object is a suitable identifier."}}}],
                      "body": {"literal": {"boolean": {}}}}}},
                {
                  "name": "supportsCustomIds",
                  "type": {
                    "annotated": {
                      "annotation": [
                        {
                          "@key": "description",
                          "@value": {
                            "literal": {
                              "string": "Determines if an Element has a specific custom object as their internal representation."}}}],
                      "body": {"literal": {"boolean": {}}}}}},
                {
                  "name": "supportsNumericIds",
                  "type": {
                    "annotated": {
                      "annotation": [
                        {
                          "@key": "description",
                          "@value": {
                            "literal": {
                              "string": "Determines if an Element has numeric identifiers as their internal representation."}}}],
                      "body": {"literal": {"boolean": {}}}}}},
                {
                  "name": "supportsRemoveProperty",
                  "type": {
                    "annotated": {
                      "annotation": [
                        {
                          "@key": "description",
                          "@value": {
                            "literal": {
                              "string": "Determines if an Element allows properties to be removed."}}}],
                      "body": {"literal": {"boolean": {}}}}}},
                {
                  "name": "supportsStringIds",
                  "type": {
                    "annotated": {
                      "annotation": [
                        {
                          "@key": "description",
                          "@value": {
                            "literal": {
                              "string": "Determines if an Element has string identifiers as their internal representation."}}}],
                      "body": {"literal": {"boolean": {}}}}}},
                {
                  "name": "supportsUserSuppliedIds",
                  "type": {
                    "annotated": {
                      "annotation": [
                        {
                          "@key": "description",
                          "@value": {
                            "literal": {
                              "string": "Determines if an Element can have a user defined identifier."}}}],
                      "body": {"literal": {"boolean": {}}}}}},
                {
                  "name": "supportsUuidIds",
                  "type": {
                    "annotated": {
                      "annotation": [
                        {
                          "@key": "description",
                          "@value": {
                            "literal": {
                              "string": "Determines if an Element has UUID identifiers as their internal representation."}}}],
                      "body": {"literal": {"boolean": {}}}}}}]}}}}},
    {
      "type": {
        "name": "hydra.ext.org.apache.tinkerpop.features.ExtraFeatures",
        "type": {
          "annotated": {
            "annotation": [
              {
                "@key": "description",
                "@value": {
                  "literal": {
                    "string": "Additional features which are needed for the complete specification of language constraints in Hydra, above and beyond TinkerPop Graph.Features"}}}],
            "body": {
              "forall": {
                "body": {
                  "record": [
                    {
                      "name": "supportsMapKey",
                      "type": {
                        "function": {
                          "codomain": {"literal": {"boolean": {}}},
                          "domain": {"variable": "hydra.core.Type"}}}}]},
                "parameter": "a"}}}}}},
    {
      "type": {
        "name": "hydra.ext.org.apache.tinkerpop.features.Features",
        "type": {
          "annotated": {
            "annotation": [
              {
                "@key": "description",
                "@value": {
                  "literal": {
                    "string": "An interface that represents the capabilities of a Graph implementation. By default all methods of features return true and it is up to implementers to disable feature they don't support. Users should check features prior to using various functions of TinkerPop to help ensure code portability across implementations. For example, a common usage would be to check if a graph supports transactions prior to calling the commit method on Graph.tx().\n\nAs an additional notice to Graph Providers, feature methods will be used by the test suite to determine which tests will be ignored and which will be executed, therefore proper setting of these features is essential to maximizing the amount of testing performed by the suite. Further note, that these methods may be called by the TinkerPop core code to determine what operations may be appropriately executed which will have impact on features utilized by users."}}}],
            "body": {
              "record": [
                {
                  "name": "edge",
                  "type": {
                    "annotated": {
                      "annotation": [
                        {
                          "@key": "description",
                          "@value": {
                            "literal": {"string": "Gets the features related to edge operation."}}}],
                      "body": {"variable": "hydra.ext.org.apache.tinkerpop.features.EdgeFeatures"}}}},
                {
                  "name": "graph",
                  "type": {
                    "annotated": {
                      "annotation": [
                        {
                          "@key": "description",
                          "@value": {
                            "literal": {"string": "Gets the features related to graph operation."}}}],
                      "body": {"variable": "hydra.ext.org.apache.tinkerpop.features.GraphFeatures"}}}},
                {
                  "name": "vertex",
                  "type": {
                    "annotated": {
                      "annotation": [
                        {
                          "@key": "description",
                          "@value": {
                            "literal": {"string": "Gets the features related to vertex operation."}}}],
                      "body": {"variable": "hydra.ext.org.apache.tinkerpop.features.VertexFeatures"}}}}]}}}}},
    {
      "type": {
        "name": "hydra.ext.org.apache.tinkerpop.features.GraphFeatures",
        "type": {
          "annotated": {
            "annotation": [
              {
                "@key": "description",
                "@value": {
                  "literal": {"string": "Features specific to a operations of a graph."}}}],
            "body": {
              "record": [
                {
                  "name": "supportsComputer",
                  "type": {
                    "annotated": {
                      "annotation": [
                        {
                          "@key": "description",
                          "@value": {
                            "literal": {
                              "string": "Determines if the Graph implementation supports GraphComputer based processing."}}}],
                      "body": {"literal": {"boolean": {}}}}}},
                {
                  "name": "supportsConcurrentAccess",
                  "type": {
                    "annotated": {
                      "annotation": [
                        {
                          "@key": "description",
                          "@value": {
                            "literal": {
                              "string": "Determines if the Graph implementation supports more than one connection to the same instance at the same time."}}}],
                      "body": {"literal": {"boolean": {}}}}}},
                {
                  "name": "supportsIoRead",
                  "type": {
                    "annotated": {
                      "annotation": [
                        {
                          "@key": "description",
                          "@value": {
                            "literal": {
                              "string": "Determines if the Graph implementations supports read operations as executed with the GraphTraversalSource.io(String) step."}}}],
                      "body": {"literal": {"boolean": {}}}}}},
                {
                  "name": "supportsIoWrite",
                  "type": {
                    "annotated": {
                      "annotation": [
                        {
                          "@key": "description",
                          "@value": {
                            "literal": {
                              "string": "Determines if the Graph implementations supports write operations as executed with the GraphTraversalSource.io(String) step."}}}],
                      "body": {"literal": {"boolean": {}}}}}},
                {
                  "name": "supportsPersistence",
                  "type": {
                    "annotated": {
                      "annotation": [
                        {
                          "@key": "description",
                          "@value": {
                            "literal": {
                              "string": "Determines if the Graph implementation supports persisting it's contents natively to disk."}}}],
                      "body": {"literal": {"boolean": {}}}}}},
                {
                  "name": "supportsThreadedTransactions",
                  "type": {
                    "annotated": {
                      "annotation": [
                        {
                          "@key": "description",
                          "@value": {
                            "literal": {
                              "string": "Determines if the Graph implementation supports threaded transactions which allow a transaction to be executed across multiple threads via Transaction.createThreadedTx()."}}}],
                      "body": {"literal": {"boolean": {}}}}}},
                {
                  "name": "supportsTransactions",
                  "type": {
                    "annotated": {
                      "annotation": [
                        {
                          "@key": "description",
                          "@value": {
                            "literal": {
                              "string": "Determines if the Graph implementations supports transactions."}}}],
                      "body": {"literal": {"boolean": {}}}}}},
                {
                  "name": "variables",
                  "type": {
                    "annotated": {
                      "annotation": [
                        {
                          "@key": "description",
                          "@value": {
                            "literal": {
                              "string": "Gets the features related to graph sideEffects operation."}}}],
                      "body": {
                        "variable": "hydra.ext.org.apache.tinkerpop.features.VariableFeatures"}}}}]}}}}},
    {
      "type": {
        "name": "hydra.ext.org.apache.tinkerpop.features.PropertyFeatures",
        "type": {
          "annotated": {
            "annotation": [
              {
                "@key": "description",
                "@value": {
                  "literal": {"string": "A base interface for Edge or Vertex Property features."}}}],
            "body": {
              "record": [
                {
                  "name": "dataTypeFeatures",
                  "type": {
                    "variable": "hydra.ext.org.apache.tinkerpop.features.DataTypeFeatures"}},
                {
                  "name": "supportsProperties",
                  "type": {
                    "annotated": {
                      "annotation": [
                        {
                          "@key": "description",
                          "@value": {
                            "literal": {
                              "string": "Determines if an Element allows for the processing of at least one data type defined by the features."}}}],
                      "body": {"literal": {"boolean": {}}}}}}]}}}}},
    {
      "type": {
        "name": "hydra.ext.org.apache.tinkerpop.features.VariableFeatures",
        "type": {
          "annotated": {
            "annotation": [
              {
                "@key": "description",
                "@value": {"literal": {"string": "Features for Graph.Variables."}}}],
            "body": {
              "record": [
                {
                  "name": "dataTypeFeatures",
                  "type": {
                    "variable": "hydra.ext.org.apache.tinkerpop.features.DataTypeFeatures"}},
                {
                  "name": "supportsVariables",
                  "type": {
                    "annotated": {
                      "annotation": [
                        {
                          "@key": "description",
                          "@value": {
                            "literal": {
                              "string": "If any of the features on Graph.Features.VariableFeatures is true then this value must be true."}}}],
                      "body": {"literal": {"boolean": {}}}}}}]}}}}},
    {
      "type": {
        "name": "hydra.ext.org.apache.tinkerpop.features.VertexFeatures",
        "type": {
          "annotated": {
            "annotation": [
              {
                "@key": "description",
                "@value": {
                  "literal": {"string": "Features that are related to Vertex operations."}}}],
            "body": {
              "record": [
                {
                  "name": "elementFeatures",
                  "type": {
                    "variable": "hydra.ext.org.apache.tinkerpop.features.ElementFeatures"}},
                {
                  "name": "properties",
                  "type": {
                    "variable": "hydra.ext.org.apache.tinkerpop.features.VertexPropertyFeatures"}},
                {
                  "name": "supportsAddVertices",
                  "type": {
                    "annotated": {
                      "annotation": [
                        {
                          "@key": "description",
                          "@value": {
                            "literal": {"string": "Determines if a Vertex can be added to the Graph."}}}],
                      "body": {"literal": {"boolean": {}}}}}},
                {
                  "name": "supportsDuplicateMultiProperties",
                  "type": {
                    "annotated": {
                      "annotation": [
                        {
                          "@key": "description",
                          "@value": {
                            "literal": {
                              "string": "Determines if a Vertex can support non-unique values on the same key."}}}],
                      "body": {"literal": {"boolean": {}}}}}},
                {
                  "name": "supportsMetaProperties",
                  "type": {
                    "annotated": {
                      "annotation": [
                        {
                          "@key": "description",
                          "@value": {
                            "literal": {
                              "string": "Determines if a Vertex can support properties on vertex properties."}}}],
                      "body": {"literal": {"boolean": {}}}}}},
                {
                  "name": "supportsMultiProperties",
                  "type": {
                    "annotated": {
                      "annotation": [
                        {
                          "@key": "description",
                          "@value": {
                            "literal": {
                              "string": "Determines if a Vertex can support multiple properties with the same key."}}}],
                      "body": {"literal": {"boolean": {}}}}}},
                {
                  "name": "supportsRemoveVertices",
                  "type": {
                    "annotated": {
                      "annotation": [
                        {
                          "@key": "description",
                          "@value": {
                            "literal": {"string": "Determines if a Vertex can be removed from the Graph."}}}],
                      "body": {"literal": {"boolean": {}}}}}},
                {
                  "name": "supportsUpsert",
                  "type": {
                    "annotated": {
                      "annotation": [
                        {
                          "@key": "description",
                          "@value": {
                            "literal": {
                              "string": "Determines if the Graph implementation uses upsert functionality as opposed to insert functionality for Graph.addVertex(String)."}}}],
                      "body": {"literal": {"boolean": {}}}}}}]}}}}},
    {
      "type": {
        "name": "hydra.ext.org.apache.tinkerpop.features.VertexPropertyFeatures",
        "type": {
          "annotated": {
            "annotation": [
              {
                "@key": "description",
                "@value": {
                  "literal": {"string": "Features that are related to Vertex Property objects."}}}],
            "body": {
              "record": [
                {
                  "name": "dataTypeFeatures",
                  "type": {
                    "variable": "hydra.ext.org.apache.tinkerpop.features.DataTypeFeatures"}},
                {
                  "name": "propertyFeatures",
                  "type": {
                    "variable": "hydra.ext.org.apache.tinkerpop.features.PropertyFeatures"}},
                {
                  "name": "elementFeatures",
                  "type": {
                    "variable": "hydra.ext.org.apache.tinkerpop.features.ElementFeatures"}},
                {
                  "name": "supportsRemove",
                  "type": {
                    "annotated": {
                      "annotation": [
                        {
                          "@key": "description",
                          "@value": {
                            "literal": {
                              "string": "Determines if a VertexProperty allows properties to be removed."}}}],
                      "body": {"literal": {"boolean": {}}}}}}]}}}}}],
  "description": [
    "A model derived from TinkerPop's Graph.Features. See\n  https://tinkerpop.apache.org/javadocs/current/core/org/apache/tinkerpop/gremlin/structure/Graph.Features.html\n\nAn interface that represents the capabilities of a Graph implementation.\nBy default all methods of features return true and it is up to implementers to disable feature they don't support.\nUsers should check features prior to using various functions of TinkerPop to help ensure code portability across implementations.\nFor example, a common usage would be to check if a graph supports transactions prior to calling the commit method on Graph.tx()."],
  "namespace": "hydra.ext.org.apache.tinkerpop.features",
  "termDependencies": ["hydra.core"],
  "typeDependencies": ["hydra.core"]}
